pygraphv/__init__.py
pygraphv/graph.py
pygraphv/html.py
pygraphv/node.py
pygraphv/style.py
pygraphv/utils.py
pygraphv-0.2.1.dist-info/LICENSE
pygraphv-0.2.1.dist-info/METADATA
pygraphv-0.2.1.dist-info/WHEEL
pygraphv-0.2.1.dist-info/top_level.txt
pygraphv-0.2.1.dist-info/RECORD
