Metadata-Version: 2.1
Name: pygraphv
Version: 0.2.1
Summary: Python library for generating dot programming language for creating graphviz graphs from python OO style code.
Home-page: https://github.com/farkon00/pygraphv
Author: farkon00
Author-email: sammer2016sammer@gmail.com
License: MIT
Classifier: Programming Language :: Python :: 3
Classifier: License :: OSI Approved :: MIT License
Classifier: Operating System :: OS Independent
Requires-Python: >=3.6
License-File: LICENSE
